[{"review":"verie nice movie rate bollywood viewers thei fight hero fight villains ' topic verie nice movie great direction verie good acting funny film good message give child feel load head parent visit stay happy day start wait 'll leave 'll leave","label":0},{"review":"thi stand movie guest 🏠 verie hat writer sharad joshi movie rector alsoemo_pos emo_pos emo_pos 👏👏","label":0},{"review":"mon feel person guest long time songs good thei give thi story child books interest children","label":0},{"review":"verie nice begin middle ding verie bad atithi stay pappu' house pappu realize hie thi hie behavior atithi verie bad verie appoint","label":0},{"review":"verie nice movie excel act verie","label":0},{"review":"' verie funny good guest home emo_pos emo_pos emo_pos","label":0},{"review":"' ally great movie full comedy joie : )","label":0},{"review":"verie good movie teach respect guardian","label":0},{"review":"verie verie nice film verie attractive loveable praiseworthy educe romantic","label":0},{"review":"movie suggest watch","label":0},{"review":"favorite ❤️ movie emo_pos 😘 ' nice","label":0},{"review":"thi verie heart touch story","label":0},{"review":"verie nice picture funny scenes top acting","label":0},{"review":"fresh comedie concept","label":0},{"review":"thi movie veru","label":0},{"review":"movie","label":0},{"review":"thi movie","label":0},{"review":"thi movie atithi tum kab jaoge watch online","label":0},{"review":"’ good movie lame","label":0},{"review":"verie film actress funny","label":0},{"review":"verry good movie","label":0},{"review":"great comedie movie","label":0},{"review":"girst movie watch theater","label":0},{"review":"awes movie","label":0},{"review":"__________","label":0}]