[{"review":"awesome... superb cast... romance a super love story, abhishek's action vijay's comedy full paisa vasool movie","label":0},{"review":"it is one of the best comedy and emotional movie ... love it...recommended my friends to watch it ....i will provide *****out of*****","label":0},{"review":"its a nice movie. run movie must be remember for fighting scenes qnd vijay raaz's comedy..","label":0},{"review":"run is a nice family movie... vijay rajs comedy is superb and unforgettable...","label":0},{"review":"run movies  story is not best , total movies is depanda only on comedy parts that done by vijay raj..ultimate comedy..i like it...","label":0},{"review":"my favourite movies. i like this picture. my  favourite actor is achieved bachchan.","label":0},{"review":"it's a awesome movie love the comedy of vijay raj","label":0},{"review":"it was a nice movie with great performance but failed to create magic due to poor editing.","label":0},{"review":"funny film good vijay raj best comedy","label":0},{"review":"this movie is romantic comedy and full of action","label":0},{"review":"nice movie n comedy by murgi","label":0},{"review":"ran move awesome move very comedy movie 😂😂😂😂😂 my name siddharth","label":0},{"review":"awesome movie paisa wasul","label":0},{"review":"i like every comedy scene","label":0},{"review":"one of my favourite movie.","label":0},{"review":"fantastic story and songs are awesome......","label":0},{"review":"super movie i really like it","label":0},{"review":"nice story, comedy, action, songs","label":0},{"review":"nice movie","label":0},{"review":"best comedy movie","label":0},{"review":"very funny scenes of vijay raaz","label":0},{"review":"super run all intresting.","label":0},{"review":"vijay raaz  awesome","label":0},{"review":"good movie indeed!!!!!!","label":0},{"review":"very funny movie.","label":0},{"review":"very comedy flim","label":0},{"review":"vijay raaz has done well in this movie","label":0},{"review":"for vijay raj","label":0},{"review":"run full movie","label":0},{"review":"real hero of movie was vijay raaz........","label":0},{"review":"naice movie","label":0},{"review":"havent watched it yet meh","label":0}]