[{"review":"ally genuine movie work sahid ayesha great movie romance comedie style movie make thi movie #dil mange mor😋emo_pos","label":1,"good":4,"bad":2,"total":18},{"review":"entertain movie intresting story shahid kapoor cute handsome thi movie song verie nice love shahid","label":1,"good":5,"bad":2,"total":15},{"review":"sail song \"aisa deewana\" awesome romantic song sonu nigam thanku sir","label":1,"good":4,"bad":1,"total":11},{"review":"verie good movie song thi movie verie good aisa deewana sonu nigam (itsmanishkumar)","label":1,"good":2,"bad":1,"total":13},{"review":"act movie shahid kapoor great movie","label":0,"good":1,"bad":1,"total":6},{"review":"thi movie story ana song","label":0,"good":0,"bad":0,"total":5},{"review":"verie nice song isha diwana hoa","label":1,"good":1,"bad":0,"total":6},{"review":"verie nice movie love","label":1,"good":2,"bad":0,"total":4},{"review":"good movie nice song","label":1,"good":2,"bad":0,"total":4},{"review":"shahid perform","label":0,"good":0,"bad":0,"total":2},{"review":"favourite movie dill manghe fell bore time thi movie","label":0,"good":2,"bad":2,"total":9},{"review":"move & act tulip joshi","label":0,"good":0,"bad":0,"total":5},{"review":"awesome movie","label":1,"good":2,"bad":0,"total":2},{"review":"thi movie super nice","label":1,"good":2,"bad":0,"total":4},{"review":"thi movie 💓","label":0,"good":0,"bad":0,"total":3},{"review":"verie nice movie","label":1,"good":1,"bad":0,"total":3},{"review":"good jabarrr dassstt","label":1,"good":1,"bad":0,"total":3}]