[{"review":"gem movie indian cinema reality true ' depict movie total love today time watch","label":1,"good":2,"bad":1,"total":14},{"review":"thi movie ally awesome ' give strong message humor ' movie story ' true fact india","label":0,"good":4,"bad":4,"total":16},{"review":"beautiful movie [ mb] verse text : /eivom evil ilpeep bm /seivom yt/moc tcilfnocsss//:sptth reverse ani text : spellbackwards(dot)","label":0,"good":1,"bad":2,"total":19},{"review":"movie scene wheee man dig hie land death hie pit emotional","label":0,"good":0,"bad":1,"total":11},{"review":"movie due hie star cast local folk songs mirror image govern system","label":0,"good":0,"bad":0,"total":12},{"review":"thi movie inspire al life state human life","label":0,"good":1,"bad":2,"total":8},{"review":"al life rector risk ofmaking type ofmovies excellent","label":1,"good":2,"bad":1,"total":8},{"review":"movie life","label":0,"good":0,"bad":0,"total":2},{"review":"movie","label":0,"good":0,"bad":0,"total":1},{"review":"character verie beautiful act amaze","label":1,"good":2,"bad":0,"total":5},{"review":"watch film medium student upcoming journalussts youth","label":0,"good":0,"bad":1,"total":7},{"review":"excel excel excel excel excel excel excel excel excel","label":1,"good":9,"bad":0,"total":9},{"review":"good movie soundtracks","label":1,"good":1,"bad":0,"total":3},{"review":"awesome movie","label":1,"good":2,"bad":0,"total":2},{"review":"super movie","label":1,"good":1,"bad":0,"total":2},{"review":"awesome movie","label":1,"good":2,"bad":0,"total":2},{"review":"good good movie","label":1,"good":2,"bad":0,"total":3},{"review":"good movie","label":1,"good":1,"bad":0,"total":2},{"review":"nice movie","label":1,"good":1,"bad":0,"total":2},{"review":"ultimate reality farmers circus medium politicians","label":0,"good":0,"bad":0,"total":6},{"review":"amaze movie","label":1,"good":1,"bad":0,"total":2},{"review":"life movie talkies peepli live","label":0,"good":0,"bad":0,"total":5},{"review":"great movie ()","label":1,"good":1,"bad":0,"total":3},{"review":"super movie","label":1,"good":1,"bad":0,"total":2},{"review":"fine grade satire pose corrupt system","label":0,"good":1,"bad":2,"total":6},{"review":"newton","label":0,"good":0,"bad":0,"total":1},{"review":"years govern medium","label":0,"good":0,"bad":0,"total":3},{"review":"perfectionist aamir khan","label":1,"good":2,"bad":0,"total":3},{"review":"organ farm","label":0,"good":0,"bad":0,"total":2},{"review":"’ true incident movie","label":0,"good":0,"bad":2,"total":4},{"review":"movie","label":0,"good":0,"bad":0,"total":1}]