[{"review":"My All Time Favourite Movie. Bobby Deol and Kangana Ranaut my favourite romantic jodi","label":0},{"review":"Today, I wathched this Movie..\nLove this movie..\nPerfect Motivational movie,..","label":0},{"review":"Rub na karen ki ye zindagi it's a very nice song and hurt touching song...","label":0},{"review":"Its song ran kare ki ye jindgi is very heart touching music","label":0},{"review":"Good movie. nice feeling after watching.","label":0},{"review":"I want to set this song as my callertune  rab na kare ke ye zindagi","label":0},{"review":"Nice song... Heart touching..","label":0},{"review":"It's interesting you should need to see once ok","label":0},{"review":"very nice movie but heroine role is time pass.......","label":0},{"review":"Where I can watch this movie?","label":0}]